mcpkmn_showdown/__init__.py
mcpkmn_showdown/data_fetcher.py
mcpkmn_showdown/data_loader.py
mcpkmn_showdown/pokemon_server.py
mcpkmn_showdown/cache/__init__.py
mcpkmn_showdown/cache/abilities.json
mcpkmn_showdown/cache/abilities_full.json
mcpkmn_showdown/cache/items.json
mcpkmn_showdown/cache/moves_showdown.json
mcpkmn_showdown/cache/pokedex.json
mcpkmn_showdown/cache/typechart.json
mcpkmn_showdown-1.0.7.dist-info/LICENSE
mcpkmn_showdown-1.0.7.dist-info/METADATA
mcpkmn_showdown-1.0.7.dist-info/WHEEL
mcpkmn_showdown-1.0.7.dist-info/entry_points.txt
mcpkmn_showdown-1.0.7.dist-info/top_level.txt
mcpkmn_showdown-1.0.7.dist-info/RECORD
