Metadata-Version: 2.2
Name: mcpkmn-showdown
Version: 1.0.7
Summary: Pokemon Showdown MCP Server - Pokemon data lookup tools for LLMs via Model Context Protocol
Author-email: Andrew Sung <drewsungg@gmail.com>
License: MIT
Project-URL: Homepage, https://github.com/drewsungg/mcpkmn-showdown
Project-URL: Repository, https://github.com/drewsungg/mcpkmn-showdown
Project-URL: Issues, https://github.com/drewsungg/mcpkmn-showdown/issues
Project-URL: License, https://github.com/drewsungg/mcpkmn-showdown?tab=MIT-1-ov-file
Keywords: pokemon,showdown,mcp,model-context-protocol,llm,claude,ai,competitive-pokemon
Classifier: Development Status :: 4 - Beta
Classifier: Intended Audience :: Developers
Classifier: License :: OSI Approved :: MIT License
Classifier: Programming Language :: Python :: 3
Classifier: Programming Language :: Python :: 3.10
Classifier: Programming Language :: Python :: 3.11
Classifier: Programming Language :: Python :: 3.12
Classifier: Topic :: Games/Entertainment
Classifier: Topic :: Scientific/Engineering :: Artificial Intelligence
Requires-Python: >=3.10
License-File: LICENSE
Requires-Dist: mcp>=1.0.0
Provides-Extra: dev
Requires-Dist: pytest>=7.0.0; extra == "dev"
Requires-Dist: pytest-cov>=4.0.0; extra == "dev"
Requires-Dist: ruff>=0.1.0; extra == "dev"
Requires-Dist: mypy>=1.0.0; extra == "dev"
